quickbot_cli/__init__.py
quickbot_cli/cli.py
quickbot_cli/templates/basic/.env.j2
quickbot_cli/templates/basic/.gitignore.j2
quickbot_cli/templates/basic/README.md.j2
quickbot_cli/templates/basic/__template__.yaml
quickbot_cli/templates/basic/pyproject.toml.j2
quickbot_cli/templates/basic/alembic/alembic.ini.j2
quickbot_cli/templates/basic/alembic/env.py.j2
quickbot_cli/templates/basic/app/config.py.j2
quickbot_cli/templates/basic/app/main.py.j2
quickbot_cli/templates/basic/app/models/__init__.py.j2
quickbot_cli/templates/basic/app/models/language.py.j2
quickbot_cli/templates/basic/app/models/role.py.j2
quickbot_cli/templates/basic/app/models/user.py.j2
quickbot_cli/templates/basic/scripts/babel_compile.sh.j2
quickbot_cli/templates/basic/scripts/babel_extract.sh.j2
quickbot_cli/templates/basic/scripts/babel_init.sh.j2
quickbot_cli/templates/basic/scripts/babel_update.sh.j2
quickbot_cli/templates/basic/scripts/migrations_apply.sh.j2
quickbot_cli/templates/basic/scripts/migrations_generate.sh.j2
quickbot_cli-0.1.1.dist-info/METADATA
quickbot_cli-0.1.1.dist-info/WHEEL
quickbot_cli-0.1.1.dist-info/entry_points.txt
quickbot_cli-0.1.1.dist-info/RECORD
