Metadata-Version: 2.4
Name: quickbot-cli
Version: 0.1.1
Summary: QuickBot CLI
Author-email: Alexander Kalinovsky <a@k8y.ru>
License: Apache-2.0
Requires-Python: >=3.13
Requires-Dist: jinja2
Requires-Dist: pyyaml
Requires-Dist: typer
Provides-Extra: dev
Requires-Dist: codespell; extra == 'dev'
Requires-Dist: mypy; extra == 'dev'
Requires-Dist: pre-commit; extra == 'dev'
Requires-Dist: pytest; extra == 'dev'
Requires-Dist: pytest-cov; extra == 'dev'
Requires-Dist: reuse; extra == 'dev'
Requires-Dist: ruff; extra == 'dev'
Requires-Dist: types-pyyaml; extra == 'dev'
